Mandark/__init__.py
Mandark/main.py
Mandark/metadata.py
Mandark/project/__init__.py
Mandark/project/app.py
Mandark/project/config.py
Mandark/project/gpg.py
Mandark/project/models.py
Mandark/project/forms/__init__.py
Mandark/project/views/__init__.py
Mandark/project/views/admin.py
Mandark/project/views/main.py
Mandark-0.0.2.dist-info/DESCRIPTION.rst
Mandark-0.0.2.dist-info/METADATA
Mandark-0.0.2.dist-info/RECORD
Mandark-0.0.2.dist-info/WHEEL
Mandark-0.0.2.dist-info/entry_points.txt
Mandark-0.0.2.dist-info/metadata.json
Mandark-0.0.2.dist-info/top_level.txt
